box_object_detection/__init__.py
box_object_detection/app.py
box_object_detection-0.1.0.dist-info/LICENSE.yaml
box_object_detection-0.1.0.dist-info/METADATA
box_object_detection-0.1.0.dist-info/WHEEL
box_object_detection-0.1.0.dist-info/entry_points.txt
box_object_detection-0.1.0.dist-info/top_level.txt
box_object_detection-0.1.0.dist-info/RECORD
