Metadata-Version: 2.1
Name: box-object-detection
Version: 0.1.0
Summary: A YOLOv8-based object detection tool using FastAPI.
Home-page: https://github.com/Raizo22
Author: Your Name
Author-email: kelessamsung22@gmail.com
License: Raizo22
Classifier: Programming Language :: Python :: 3
Classifier: License :: OSI Approved :: MIT License
Classifier: Operating System :: OS Independent
Requires-Python: >=3.8
License-File: LICENSE.yaml
Requires-Dist: fastapi
Requires-Dist: uvicorn
Requires-Dist: pillow
Requires-Dist: opencv-python
Requires-Dist: numpy
Requires-Dist: ultralytics
